code_insight_api_py/__init__.py
code_insight_api_py/client.py
code_insight_api_py/tests/test_client.py
code_insight_api_py-0.1.0.dist-info/LICENSE
code_insight_api_py-0.1.0.dist-info/METADATA
code_insight_api_py-0.1.0.dist-info/WHEEL
code_insight_api_py-0.1.0.dist-info/RECORD
