Metadata-Version: 2.1
Name: code-insight-api-py
Version: 0.1.0
Summary: 
Author: Zachary Karpinski
Author-email: 1206496+zkarpinski@users.noreply.github.com
Requires-Python: >=3.9,<4.0
Classifier: Programming Language :: Python :: 3
Classifier: Programming Language :: Python :: 3.9
Classifier: Programming Language :: Python :: 3.10
Classifier: Programming Language :: Python :: 3.11
Requires-Dist: argparse (>=1.4.0,<2.0.0)
Requires-Dist: requests (>=2.31.0,<3.0.0)
